algo/__init__.py
algo/__main__.py
algo/config.py
algo/constant.py
algo/indicator.py
algo/public.py
algo/simulation.py
algo/util.py
algo/data/__init__.py
algo/data/cache.py
algo/data/common.py
algo/data/connection.py
algo/data/live.py
algo/data/reader.py
algo/data/reporter.py
algo/strategy/__init__.py
algo/strategy/common.py
algo/strategy/moving_averages.py
algo/trading/__init__.py
algo/trading/oanda.py
algo/trading/state.py
trade_utils-1.0.1.dist-info/LICENSE
trade_utils-1.0.1.dist-info/METADATA
trade_utils-1.0.1.dist-info/WHEEL
trade_utils-1.0.1.dist-info/top_level.txt
trade_utils-1.0.1.dist-info/RECORD
