Metadata-Version: 2.1
Name: trade-utils
Version: 1.0.1
Summary: Algo trading utils package. Zero test-coverage so use on your own risk.
Home-page: https://github.com/darnes/algo
Author: darnes
Author-email: darnesmeister@gmail.com
License: MIT
Classifier: Programming Language :: Python :: 3
Classifier: License :: OSI Approved :: MIT License
Classifier: Operating System :: OS Independent
Requires-Python: >=3.9
License-File: LICENSE
Requires-Dist: v20
Requires-Dist: pyyaml
Requires-Dist: influxdb
Requires-Dist: influxdb-client
Requires-Dist: python-json-logger
Requires-Dist: iso8601
Requires-Dist: rfc3339
Requires-Dist: redis
